filemindr/__init__.py
filemindr/cli.py
filemindr/py.typed
filemindr/core/__init__.py
filemindr/core/config.py
filemindr/core/runner.py
filemindr-0.1.0.dist-info/METADATA
filemindr-0.1.0.dist-info/WHEEL
filemindr-0.1.0.dist-info/entry_points.txt
filemindr-0.1.0.dist-info/RECORD
