Metadata-Version: 2.4
Name: filemindr
Version: 0.1.0
Summary: Declarative local file pipelines in Python
Author: Jeferson Peter
Requires-Python: >=3.12
Requires-Dist: loguru
Requires-Dist: pydantic-settings
Requires-Dist: pyyaml
Requires-Dist: typer
Provides-Extra: dev
Requires-Dist: pytest>=8; extra == 'dev'
Requires-Dist: ruff>=0.5; extra == 'dev'
